pycottas_endpoint/__init__.py
pycottas_endpoint/__main__.py
pycottas_endpoint/sparql_endpoint.py
pycottas_endpoint/sparql_router.py
pycottas_endpoint/utils.py
pycottas_endpoint/yasgui.html
pycottas_endpoint-0.5.3.dist-info/METADATA
pycottas_endpoint-0.5.3.dist-info/WHEEL
pycottas_endpoint-0.5.3.dist-info/entry_points.txt
pycottas_endpoint-0.5.3.dist-info/licenses/LICENSE.txt
pycottas_endpoint-0.5.3.dist-info/RECORD
