Metadata-Version: 2.4
Name: pycottas-endpoint
Version: 0.5.3
Summary: A package to deploy SPARQL endpoint to serve local COTTAS files, using RDFLib and FastAPI.
Project-URL: Homepage, https://github.com/arenas-guerrero-julian/pycottas-endpoint
Project-URL: Documentation, https://github.com/arenas-guerrero-julian/pycottas-endpoint
Project-URL: History, https://github.com/arenas-guerrero-julian/pycottas-endpoint/releases
Project-URL: Tracker, https://github.com/arenas-guerrero-julian/pycottas-endpoint/issues
Project-URL: Source, https://github.com/arenas-guerrero-julian/pycottas-endpoint
Author-email: Vincent Emonet <vincent.emonet@gmail.com>, Julián Arenas-Guerrero <julian.arenas.guerrero@upm.es>
Maintainer-email: Vincent Emonet <vincent.emonet@gmail.com>, Julián Arenas-Guerrero <julian.arenas.guerrero@upm.es>
License: MIT License
License-File: LICENSE.txt
Keywords: COTTAS,Python,RDF,SPARQL,endpoint
Classifier: License :: OSI Approved :: MIT License
Classifier: Operating System :: OS Independent
Classifier: Programming Language :: Python :: 3
Classifier: Programming Language :: Python :: 3.8
Classifier: Programming Language :: Python :: 3.9
Classifier: Programming Language :: Python :: 3.10
Classifier: Programming Language :: Python :: 3.11
Classifier: Programming Language :: Python :: 3.12
Classifier: Programming Language :: Python :: 3.13
Requires-Python: >=3.8
Requires-Dist: fastapi<2.0.0,>=0.51.0
Requires-Dist: pycottas<2.0.0,>=1.0.0
Requires-Dist: rdflib<8.0.0,>=6.0.0
Provides-Extra: cli
Requires-Dist: click; extra == 'cli'
Requires-Dist: uvicorn[standard]>=0.12.0; extra == 'cli'
Provides-Extra: web
Requires-Dist: uvicorn[standard]>=0.12.0; extra == 'web'
